<?xml version = '1.0' encoding = 'UTF-8'?>
<FKIndexAssociation class="oracle.dbtools.crest.model.design.relational.FKIndexAssociation" directorySegmentName="seg_0" id="A801F784-A925-7F43-F064-7E95B8AC008D" containerWithKeyObject="485CE7D6-B51A-D9CE-36A0-DDD4AAB306F7" localFKIndex="809BCFEC-B2D6-61BB-C094-437735E4AE9F" name="INVENBODEGA_DISPOSITIVOS_FK">
<createdBy>auxsoporte1</createdBy>
<createdTime>2018-07-30 22:10:40 UTC</createdTime>
<ownerDesignName>SMIT_datamodeler</ownerDesignName>
<referredTableLongName>DISPOSITIVOS</referredTableLongName>
<deleteRule>NO ACTION</deleteRule>
<referredTableID>9450E49B-5810-06CD-DC8F-05ECEE2F2D9B</referredTableID>
<keyObject>2E5B3E09-F2D7-4CEC-E593-6B666F4EC736</keyObject>
<referredKeyID>2E5B3E09-F2D7-4CEC-E593-6B666F4EC736</referredKeyID>
<mandatory>false</mandatory>
<refColNames>DISPO_SERIAL_V</refColNames>
<transferable>true</transferable>
<rely>false</rely>
<columnDependencyConstraintGenerateInDDL>true</columnDependencyConstraintGenerateInDDL>
</FKIndexAssociation>